superchain/__init__.py
superchain/chain.py
superchain/ying.py
superchain/tests/__init__.py
superchain/tests/tests.py
superchain-0.1.0.dist-info/METADATA
superchain-0.1.0.dist-info/RECORD
superchain-0.1.0.dist-info/WHEEL
superchain-0.1.0.dist-info/top_level.txt
