Metadata-Version: 2.1
Name: superchain
Version: 0.1.0
Summary: A complex chained relational data structure
Home-page: https://github.com/yunlongying/SuperChain.git
Author: yingyunlong
Author-email: fengyuan1210@163.com
License: MIT Licence
Keywords: pip,superchain
Platform: any
